bingx/__init__.py
bingx/ccxt/__init__.py
bingx/ccxt/bingx.py
bingx/ccxt/abstract/bingx.py
bingx/ccxt/async_support/__init__.py
bingx/ccxt/async_support/bingx.py
bingx/ccxt/async_support/base/__init__.py
bingx/ccxt/async_support/base/exchange.py
bingx/ccxt/async_support/base/throttler.py
bingx/ccxt/async_support/base/ws/__init__.py
bingx/ccxt/async_support/base/ws/cache.py
bingx/ccxt/async_support/base/ws/client.py
bingx/ccxt/async_support/base/ws/functions.py
bingx/ccxt/async_support/base/ws/future.py
bingx/ccxt/async_support/base/ws/order_book.py
bingx/ccxt/async_support/base/ws/order_book_side.py
bingx/ccxt/base/__init__.py
bingx/ccxt/base/decimal_to_precision.py
bingx/ccxt/base/errors.py
bingx/ccxt/base/exchange.py
bingx/ccxt/base/precise.py
bingx/ccxt/base/types.py
bingx/ccxt/pro/__init__.py
bingx/ccxt/pro/bingx.py
bingx/ccxt/static_dependencies/README.md
bingx/ccxt/static_dependencies/__init__.py
bingx/ccxt/static_dependencies/bip/__init__.py
bingx/ccxt/static_dependencies/bip/addr/P2PKH_addr.py
bingx/ccxt/static_dependencies/bip/addr/__init__.py
bingx/ccxt/static_dependencies/bip/addr/addr_dec_utils.py
bingx/ccxt/static_dependencies/bip/addr/addr_key_validator.py
bingx/ccxt/static_dependencies/bip/addr/iaddr_decoder.py
bingx/ccxt/static_dependencies/bip/addr/iaddr_encoder.py
bingx/ccxt/static_dependencies/bip/base58/__init__.py
bingx/ccxt/static_dependencies/bip/base58/base58.py
bingx/ccxt/static_dependencies/bip/base58/base58_ex.py
bingx/ccxt/static_dependencies/bip/base58/base58_xmr.py
bingx/ccxt/static_dependencies/bip/bech32/__init__.py
bingx/ccxt/static_dependencies/bip/bech32/bch_bech32.py
bingx/ccxt/static_dependencies/bip/bech32/bech32.py
bingx/ccxt/static_dependencies/bip/bech32/bech32_base.py
bingx/ccxt/static_dependencies/bip/bech32/bech32_ex.py
bingx/ccxt/static_dependencies/bip/bech32/segwit_bech32.py
bingx/ccxt/static_dependencies/bip/bip32/__init__.py
bingx/ccxt/static_dependencies/bip/bip32/bip32_const.py
bingx-0.0.120.dist-info/METADATA
bingx-0.0.120.dist-info/WHEEL
bingx-0.0.120.dist-info/RECORD
